bumph/__init__.py
bumph-0.0.2.dist-info/LICENSE
bumph-0.0.2.dist-info/METADATA
bumph-0.0.2.dist-info/WHEEL
bumph-0.0.2.dist-info/top_level.txt
bumph-0.0.2.dist-info/RECORD
