Metadata-Version: 2.1
Name: bumph
Version: 0.0.2
Summary: Simple mapping view to docx (Word Doc) elements
Home-page: https://github.com/thorwhalen/bumph
Author: Thor Whalen
License: apache-2.0
Keywords: docx,doc file,microsoft word,msword
Platform: any
Requires-Dist: py2store
Requires-Dist: python-docx
